tdautils/__init__.py
tdautils/data/non_tradedate_A.py
tdautils-1.1.11.dist-info/METADATA
tdautils-1.1.11.dist-info/WHEEL
tdautils-1.1.11.dist-info/top_level.txt
tdautils-1.1.11.dist-info/RECORD
