Metadata-Version: 2.1
Name: tdautils
Version: 1.1.11
Summary: A trade date generator for quant model of Chinese stock market
Home-page: https://github.com/edwincca/stockpriceanna/blob/master/README.md
Author: DrEdwC
Author-email: ed@topfintech.org
License: UNKNOWN
Platform: UNKNOWN
Classifier: Programming Language :: Python :: 3
Classifier: License :: OSI Approved :: MIT License
Classifier: Operating System :: OS Independent
